hb_account_statement_banque_postale_csv/__init__.py
hb_account_statement_banque_postale_csv/account.py
hb_account_statement_banque_postale_csv/configuration.py
hb_account_statement_banque_postale_csv/configuration.xml
hb_account_statement_banque_postale_csv/tryton.cfg
hb_account_statement_banque_postale_csv/view/configuration_form.xml
tests/01.csv
tests/02.csv
tests/__init__.py
tests/scenario_account_statement_banque_postale_csv_new.rst
tests/scenario_account_statement_banque_postale_csv_old.rst
tests/test_hb_account_statement_banque_postale_csv.py
hb_account_statement_banque_postale_csv-0.3.1.dist-info/LICENSE
hb_account_statement_banque_postale_csv-0.3.1.dist-info/METADATA
hb_account_statement_banque_postale_csv-0.3.1.dist-info/WHEEL
hb_account_statement_banque_postale_csv-0.3.1.dist-info/entry_points.txt
hb_account_statement_banque_postale_csv-0.3.1.dist-info/top_level.txt
hb_account_statement_banque_postale_csv-0.3.1.dist-info/RECORD
