Metadata-Version: 2.1
Name: hb-account-statement-banque-postale-csv
Version: 0.3.1
Home-page: https://hashbang.fr/
Author: Hashbang
Author-email: contact@hashbang.fr
License: GPL-3
Project-URL: Bug Tracker, https://gitlab.com/hashbangfr/tryton-modules/hb_account_statement_banque_postale_csv/-/issues
Project-URL: Source Code, https://gitlab.com/hashbangfr/tryton-modules/hb_account_statement_banque_postale_csv/
Keywords: tryton,banque postale
Classifier: Development Status :: 5 - Production/Stable
Classifier: Environment :: Plugins
Classifier: Framework :: Tryton
Classifier: Intended Audience :: Developers
Classifier: Intended Audience :: Financial and Insurance Industry
Classifier: Intended Audience :: Legal Industry
Classifier: License :: OSI Approved :: GNU General Public License v3 or later (GPLv3+)
Classifier: Operating System :: OS Independent
Classifier: Programming Language :: Python :: 3
Classifier: Programming Language :: Python :: 3.6
Classifier: Programming Language :: Python :: 3.7
Classifier: Programming Language :: Python :: 3.8
Classifier: Programming Language :: Python :: 3.9
Classifier: Programming Language :: Python :: Implementation :: CPython
Classifier: Programming Language :: Python :: Implementation :: PyPy
Classifier: Topic :: Office/Business
Requires-Python: >=3.6
License-File: LICENSE
Requires-Dist: wheel
Requires-Dist: tryton
Requires-Dist: trytond
Requires-Dist: trytond-account-statement
